image_processing_dio/__init__.py
image_processing_dio/processing/__init__.py
image_processing_dio/processing/combination.py
image_processing_dio/processing/transformation.py
image_processing_dio/utils/__init__.py
image_processing_dio/utils/io.py
image_processing_dio/utils/plot.py
image_processing_mmc/__init__.py
image_processing_mmc/processing/__init__.py
image_processing_mmc/processing/combination.py
image_processing_mmc/processing/transformation.py
image_processing_mmc/utils/__init__.py
image_processing_mmc/utils/io.py
image_processing_mmc/utils/plot.py
image_processing_mmc-0.0.4.dist-info/METADATA
image_processing_mmc-0.0.4.dist-info/WHEEL
image_processing_mmc-0.0.4.dist-info/top_level.txt
image_processing_mmc-0.0.4.dist-info/RECORD
