Metadata-Version: 2.1
Name: image-processing-mmc
Version: 0.0.4
Summary: Image Processing Package using Skimage
Home-page: https://github.com/monicacaetano/image_processing_dio_unimed.git
Author: monicacaetano
Author-email: monica02caetano@gmail.com
Requires-Python: >=3.8
Requires-Dist: matplotlib
Requires-Dist: numpy
Requires-Dist: scikit-image (>=0.16.1)
